mol_inspector/__init__.py
mol_inspector/inspector.py
mol_inspector/plot.py
mol_inspector/utils.py
mol_inspector-0.0.1.dist-info/LICENSE
mol_inspector-0.0.1.dist-info/METADATA
mol_inspector-0.0.1.dist-info/WHEEL
mol_inspector-0.0.1.dist-info/RECORD
