Metadata-Version: 2.3
Name: mol-inspector
Version: 0.0.1
Summary: Inspect Molecular ML Models Using SHAP
License: MIT
Author: Tony Eight Lin
Author-email: tonyelin@tmu.edu.tw
Requires-Python: >=3.10
Classifier: License :: OSI Approved :: MIT License
Classifier: Programming Language :: Python :: 3
Classifier: Programming Language :: Python :: 3.10
Classifier: Programming Language :: Python :: 3.11
Classifier: Programming Language :: Python :: 3.12
Classifier: Programming Language :: Python :: 3.13
Requires-Dist: ipywidgets (>=8.1.7)
Requires-Dist: keras (>=3.0.0)
Requires-Dist: notebook (==7.0.6)
Requires-Dist: rdkit (>=2024.3.2)
Requires-Dist: seaborn (>=0.13.0)
Requires-Dist: shap (>=0.47.2)
Requires-Dist: torch (>=2.7.0)
Requires-Dist: xgboost (>=3.0.0)
Project-URL: Repository, https://github.com/tlint101/mol-inspector.git
